{
  "favorites": [],
  "lookup_history": [
    "item:thermal:nickel_gear",
    "item:farmersdelight:cooking_pot",
    "item:vintageimprovements:small_constantan_spring",
    "item:thermal:raw_nickel",
    "item:thermal:nickel_ingot",
    "item:thermal:nickel_coin",
    "item:cmi:handheld_crafting_table",
    "#item:forge:workbenches",
    "item:minecraft:birch_fence",
    "item:tconstruct:crafting_station",
    "item:minecraft:crafting_table",
    "item:cmi:water_well",
    "item:ad_astra:wrench",
    "item:cmi:space_elevator_base_console",
    "item:cmi:test_coke_oven",
    "item:cmi:steam_hammer",
    "item:custommachinery:custom_machine_item",
    "item:minecraft:bamboo_slab",
    {
      "type": "jemi",
      "uid": "nebula_tinker:abuser"
    },
    "item:create:brass_casing",
    {
      "type": "list",
      "amount": 50,
      "ingredients": [
        "fluid:createdieselgenerators:gasoline",
        "fluid:thermal:refined_fuel",
        "fluid:tconstruct:blazing_blood",
        "fluid:minecraft:lava",
        "fluid:ad_astra:cryo_fuel",
        "#fluid:forge:fuel"
      ]
    },
    {
      "type": "fluid",
      "id": "minecraft:lava",
      "amount": 100
    },
    "item:cmi:stone_plate",
    "item:cmi:flint_hammer{Damage:0}",
    "item:mbtool:mbtool",
    "item:immersiveindustry:crucible",
    {
      "type": "jemi",
      "uid": "tconstruct:smite"
    },
    "item:cmi:steel_ingot",
    "item:minecraft:obsidian",
    "item:minecraft:torch",
    "item:minecraft:water_bucket",
    "item:minecraft:oak_stairs",
    "item:cmi:blood_slime_ball",
    "item:cmi:grass_fiber",
    "item:minecraft:crying_obsidian",
    "item:cmi:tier_1_rocket_nose_cone",
    "item:cmi:tier_1_rocket_fin",
    [
      {
        "type": "fluid",
        "id": "cmi:sea_water",
        "amount": 2147483647
      },
      "item:cmi:sea_water_bucket"
    ],
    "item:minecraft:spruce_wood",
    "item:cmi:togni_leets",
    "item:vintageimprovements:small_zinc_spring"
  ],
  "craft_history": [],
  "recipe_defaults": {
    "added": [],
    "tags": {},
    "resolutions": {},
    "disabled": [
      "jei:/railways/mixing/palettes/dyeing/brown_slashed_locometal",
      "jei:/railways/mixing/palettes/dyeing/lime_iron_wrapped_locometal_boiler",
      "jei:/railways/mixing/palettes/dyeing/pine_green_iron_wrapped_locometal_boiler",
      "jei:/railways/mixing/palettes/dyeing/pink_iron_wrapped_locometal_boiler"
    ]
  },
  "hidden_stacks": [
    "item:cmi:diamond_hammer{Damage:0}"
  ]
}